{"truncated": true, "id": 994933735962312704, "possibly_sensitive": false, "created_at": "Fri May 11 13:34:22 +0000 2018", "entities": {"user_mentions": [], "symbols": [], "hashtags": [{"text": "accountmanagement", "indices": [19, 37]}, {"text": "revenue", "indices": [106, 114]}], "urls": [{"url": "https://t.co/IZnfPPtJTE", "display_url": "twitter.com/i/web/status/9\u2026", "expanded_url": "https://twitter.com/i/web/status/994933735962312704", "indices": [117, 140]}]}, "geo": null, "text": "Do you have killer #accountmanagement skills? Love to work with clients on strategy that will drive major #revenue?\u2026 https://t.co/IZnfPPtJTE", "source": "<a href=\"http://twitter.com\" rel=\"nofollow\">Twitter Web Client</a>", "in_reply_to_status_id_str": null, "contributors": null, "in_reply_to_user_id_str": null, "coordinates": null, "retweet_count": 0, "retweeted": false, "favorite_count": 1, "metadata": {"iso_language_code": "en", "result_type": "recent"}, "in_reply_to_screen_name": null, "in_reply_to_user_id": null, "user": {"profile_sidebar_fill_color": "E3E2DE", "utc_offset": -14400, "id": 120609474, "protected": false, "profile_use_background_image": true, "profile_banner_url": "https://pbs.twimg.com/profile_banners/120609474/1524840778", "profile_image_url": "http://pbs.twimg.com/profile_images/460841057198931969/ji6oRO5h_normal.png", "has_extended_profile": false, "verified": false, "created_at": "Sun Mar 07 00:30:44 +0000 2010", "statuses_count": 364, "default_profile": false, "is_translator": false, "entities": {"url": {"urls": [{"url": "http://t.co/XQMEV0FZ46", "display_url": "BounceX.com", "expanded_url": "http://www.BounceX.com", "indices": [0, 22]}]}, "description": {"urls": []}}, "url": "http://t.co/XQMEV0FZ46", "geo_enabled": false, "profile_sidebar_border_color": "FFFFFF", "default_profile_image": false, "description": "BounceX is the first new revenue channel with scale in years. Our PBM & Identification tech offers brands a meaningful paid channel outside Google and Facebook.", "profile_image_url_https": "https://pbs.twimg.com/profile_images/460841057198931969/ji6oRO5h_normal.png", "profile_background_image_url_https": "https://pbs.twimg.com/profile_background_images/460840656634527744/t5uZZi_9.png", "favourites_count": 2094, "profile_background_tile": true, "profile_background_image_url": "http://pbs.twimg.com/profile_background_images/460840656634527744/t5uZZi_9.png", "screen_name": "BounceExchange", "following": false, "time_zone": "Eastern Time (US & Canada)", "location": "Made in Silicon Alley", "followers_count": 2161, "listed_count": 84, "profile_link_color": "7BA5CA", "follow_request_sent": false, "lang": "en", "friends_count": 1165, "id_str": "120609474", "profile_text_color": "634047", "name": "BounceX", "is_translation_enabled": false, "translator_type": "none", "profile_background_color": "EDECE9", "contributors_enabled": false, "notifications": false}, "id_str": "994933735962312704", "in_reply_to_status_id": null, "lang": "en", "is_quote_status": false, "place": null, "favorited": false}